MainFuncLib/MainFunction.py
MainFuncLib/Portfolio.py
MainFuncLib/__init__.py
MainFuncLib-0.3.8.dist-info/METADATA
MainFuncLib-0.3.8.dist-info/WHEEL
MainFuncLib-0.3.8.dist-info/top_level.txt
MainFuncLib-0.3.8.dist-info/RECORD
