Metadata-Version: 2.1
Name: MainFuncLib
Version: 0.3.8
Summary: Demo library
Home-page: https://MainFuncLib.readthedocs.io/
Author: Rob Windey
Author-email: rw3333@nyu.edu
License: MIT
Classifier: Intended Audience :: Developers
Classifier: License :: OSI Approved :: MIT License
Classifier: Programming Language :: Python
Classifier: Programming Language :: Python :: 3.8
Classifier: Programming Language :: Python :: 3.9
Classifier: Operating System :: OS Independent
Requires-Dist: sqlalchemy
Requires-Dist: polygon
